[
  {
    "Name": "Unobtanium",
    "Requirements": [
    ]
  },
  {
    "Name": "Carbon",
    "Requirements": [
    ]
  },
  {
    "Name": "Steel Block",
    "Requirements": [
    ]
  },
  {
    "Name": "Steel Plate",
    "Requirements": [
      {
        "Name": "Steel Block",
        "Number": 2
      },
      {
        "Name": "Carbon",
        "Number": 5
      }
    ]
  },
  {
    "Name": "Steel Rod",
    "Requirements": [
      {
        "Name": "Steel Block",
        "Number": 1
      }
    ]
  }
]